GTAlib_MonteCarlo/__init__.py
GTAlib_MonteCarlo/modulo.py
GTAlib_MonteCarlo-0.1.2.dist-info/METADATA
GTAlib_MonteCarlo-0.1.2.dist-info/WHEEL
GTAlib_MonteCarlo-0.1.2.dist-info/top_level.txt
GTAlib_MonteCarlo-0.1.2.dist-info/RECORD
