Metadata-Version: 2.1
Name: GTAlib-MonteCarlo
Version: 0.1.2
Summary: Libreria para calcular la integral definida sobre de un intérvalo de una funcion
Home-page: https://gitlab.com/gtorresa312/trabajos-en-clase.git
Author: German
Author-email: german.torres@udea.edu.co
License: MIT
Requires-Python: >=3.11.6
Requires-Dist: numpy ==1.26.1
